[
    [
        {
            "comment": "",
            "name": "time taken",
            "network_parameters": {
                "activation_function": "relu",
                "bias": true,
                "layers": [
                    784,
                    50,
                    10
                ],
                "learning_rate": [
                    0.001,
                    0.001
                ],
                "n_synapses": [
                    39200.0,
                    500.0
                ],
                "p_connect": [
                    1.0,
                    1.0
                ]
            },
            "results": {
                "accuracy": [
                    78.39,
                    83.94,
                    85.42999999999999,
                    86.82,
                    87.46000000000001,
                    88.03,
                    88.77000000000001,
                    88.85,
                    89.27000000000001,
                    89.66,
                    89.88000000000001
                ],
                "energy": [
                    636.0259719660521,
                    1048.1948106161906,
                    1370.5435101405576,
                    1691.732673421465,
                    1998.0117416796209,
                    2287.7917723954934,
                    2566.1255692899285,
                    2853.276463335397,
                    3133.7912234956434,
                    3387.488550545764,
                    3654.1853272260155
                ],
                "error": [
                    1.5764707157654032,
                    1.39022134324644,
                    1.3071291153226137,
                    1.2315260806279689,
                    1.16147804864647,
                    1.1198313910295281,
                    1.0792527103028269,
                    1.0598101953986185,
                    1.0364148189930507,
                    1.0078005945584159,
                    0.9928014272972827
                ],
                "min_energy": [
                    0.6183312401279559,
                    1.38026046377138,
                    2.2113583846253393,
                    3.126456369984072,
                    4.119923986187627,
                    5.174520521895246,
                    6.265361082229138,
                    7.404358110424786,
                    8.583772542001498,
                    9.816671339275032,
                    11.095947113088018
                ],
                "samples_seen": [
                    [
                        5000.0,
                        10000.0,
                        15000.0,
                        20000.0,
                        25000.0,
                        30000.0,
                        35000.0,
                        40000.0,
                        45000.0,
                        50000.0,
                        55000.0
                    ],
                    [
                        1961.0,
                        3003.0,
                        3784.0,
                        4519.0,
                        5213.0,
                        5857.0,
                        6460.0,
                        7078.0,
                        7676.0,
                        8214.0,
                        8767.0
                    ]
                ]
            }
        },
        {
            "comment": "",
            "name": "time taken",
            "network_parameters": {
                "activation_function": "relu",
                "bias": true,
                "layers": [
                    784,
                    100,
                    10
                ],
                "learning_rate": [
                    0.001,
                    0.001
                ],
                "n_synapses": [
                    78400.0,
                    1000.0
                ],
                "p_connect": [
                    1.0,
                    1.0
                ]
            },
            "results": {
                "accuracy": [
                    79.27,
                    82.86,
                    85.57000000000001,
                    87.57000000000001,
                    88.31,
                    88.33,
                    89.44,
                    89.02,
                    89.72,
                    90.21000000000001,
                    90.23
                ],
                "energy": [
                    807.3998795851398,
                    1261.7359786669583,
                    1688.6365158565336,
                    2091.4255052892345,
                    2475.760636269527,
                    2838.223778011694,
                    3190.5026807378604,
                    3548.8962995185166,
                    3898.5261270402857,
                    4248.664445387781,
                    4592.583391009861
                ],
                "error": [
                    1.6876248410829744,
                    1.5045183867228649,
                    1.383972442079974,
                    1.2780042581105833,
                    1.2044332680877061,
                    1.1552864912147702,
                    1.1058941723341718,
                    1.083582681760402,
                    1.048196040888955,
                    1.0282216779866284,
                    1.000534365472052
                ],
                "min_energy": [
                    0.6540157360707115,
                    1.5292180909770747,
                    2.5541458803387984,
                    3.740898607764751,
                    5.039380879806536,
                    6.431938761669431,
                    7.908093076620804,
                    9.459942546415169,
                    11.081601522018326,
                    12.7609674400875,
                    14.529711323908632
                ],
                "samples_seen": [
                    [
                        5000.0,
                        10000.0,
                        15000.0,
                        20000.0,
                        25000.0,
                        30000.0,
                        35000.0,
                        40000.0,
                        45000.0,
                        50000.0,
                        55000.0
                    ],
                    [
                        1883.0,
                        2813.0,
                        3600.0,
                        4322.0,
                        4989.0,
                        5599.0,
                        6181.0,
                        6740.0,
                        7297.0,
                        7837.0,
                        8381.0
                    ]
                ]
            }
        },
        {
            "comment": "",
            "name": "time taken",
            "network_parameters": {
                "activation_function": "relu",
                "bias": true,
                "layers": [
                    784,
                    150,
                    10
                ],
                "learning_rate": [
                    0.001,
                    0.001
                ],
                "n_synapses": [
                    117600.0,
                    1500.0
                ],
                "p_connect": [
                    1.0,
                    1.0
                ]
            },
            "results": {
                "accuracy": [
                    79.63,
                    83.8,
                    86.1,
                    87.64,
                    88.47,
                    88.6,
                    89.17,
                    89.61,
                    90.44,
                    90.85,
                    90.75999999999999
                ],
                "energy": [
                    959.0338236945532,
                    1477.6804453310374,
                    1936.3993630865884,
                    2338.1280562577554,
                    2799.694087572466,
                    3214.726140794444,
                    3625.417757667138,
                    4031.999213428831,
                    4423.959513345929,
                    4775.538691643287,
                    5138.852309501055
                ],
                "error": [
                    1.7124253527283635,
                    1.5340563037781356,
                    1.4117977069190772,
                    1.321661734097827,
                    1.2486615952771363,
                    1.1801411732732034,
                    1.1366356432832527,
                    1.0927669029983333,
                    1.0627492111211756,
                    1.0337548119352564,
                    1.0102632558408848
                ],
                "min_energy": [
                    0.6915813463386198,
                    1.5964615469395418,
                    2.6513864848427673,
                    3.8150068739524507,
                    5.093313221153873,
                    6.467328128934906,
                    7.9326856372303025,
                    9.477880593379671,
                    11.084118228889993,
                    12.7346479688535,
                    14.45043576069009
                ],
                "samples_seen": [
                    [
                        5000.0,
                        10000.0,
                        15000.0,
                        20000.0,
                        25000.0,
                        30000.0,
                        35000.0,
                        40000.0,
                        45000.0,
                        50000.0,
                        55000.0
                    ],
                    [
                        1938.0,
                        2866.0,
                        3638.0,
                        4278.0,
                        4992.0,
                        5615.0,
                        6211.0,
                        6790.0,
                        7350.0,
                        7842.0,
                        8351.0
                    ]
                ]
            }
        },
        {
            "comment": "",
            "name": "time taken",
            "network_parameters": {
                "activation_function": "relu",
                "bias": true,
                "layers": [
                    784,
                    200,
                    10
                ],
                "learning_rate": [
                    0.001,
                    0.001
                ],
                "n_synapses": [
                    156800.0,
                    2000.0
                ],
                "p_connect": [
                    1.0,
                    1.0
                ]
            },
            "results": {
                "accuracy": [
                    79.22,
                    84.77,
                    86.69,
                    87.71,
                    88.73,
                    88.87,
                    89.14999999999999,
                    89.71000000000001,
                    90.52,
                    89.89,
                    90.64999999999999
                ],
                "energy": [
                    1043.5146146856655,
                    1606.923940972303,
                    2124.378234454549,
                    2651.6006454997946,
                    3118.578868856822,
                    3586.199151332783,
                    4042.417629030489,
                    4464.71020232379,
                    4916.202615652843,
                    5333.142763220198,
                    5766.971083837811
                ],
                "error": [
                    1.7160572847618791,
                    1.5399076056425494,
                    1.416821674316169,
                    1.3222266306032695,
                    1.2506975857761584,
                    1.1967195974628593,
                    1.1522974000811372,
                    1.1135785290958276,
                    1.0708797935723382,
                    1.0609747013204816,
                    1.0157942990076312
                ],
                "min_energy": [
                    0.8214819617152868,
                    1.8927519368936863,
                    3.160829112354528,
                    4.564957714957365,
                    6.085478380882207,
                    7.740606709445914,
                    9.452034817719403,
                    11.263334643040148,
                    13.156164961769901,
                    15.130079241574471,
                    17.172371827753842
                ],
                "samples_seen": [
                    [
                        5000.0,
                        10000.0,
                        15000.0,
                        20000.0,
                        25000.0,
                        30000.0,
                        35000.0,
                        40000.0,
                        45000.0,
                        50000.0,
                        55000.0
                    ],
                    [
                        1768.0,
                        2636.0,
                        3390.0,
                        4099.0,
                        4704.0,
                        5296.0,
                        5857.0,
                        6371.0,
                        6907.0,
                        7400.0,
                        7908.0
                    ]
                ]
            }
        },
        {
            "comment": "",
            "name": "time taken",
            "network_parameters": {
                "activation_function": "relu",
                "bias": true,
                "layers": [
                    784,
                    250,
                    10
                ],
                "learning_rate": [
                    0.001,
                    0.001
                ],
                "n_synapses": [
                    196000.0,
                    2500.0
                ],
                "p_connect": [
                    1.0,
                    1.0
                ]
            },
            "results": {
                "accuracy": [
                    79.63,
                    85.02,
                    86.69,
                    86.78,
                    88.05,
                    89.13,
                    88.59,
                    89.73,
                    90.38000000000001,
                    89.98,
                    89.81
                ],
                "energy": [
                    1143.1365150243762,
                    1867.1368789138899,
                    2468.344855965812,
                    3029.585832480233,
                    3582.5472843295606,
                    4131.5872684276455,
                    4642.004456400207,
                    5151.757882338377,
                    5657.021565693756,
                    6113.940438950751,
                    6604.46577485385
                ],
                "error": [
                    1.681612051379924,
                    1.4749983661776331,
                    1.3572737829671404,
                    1.280478983050607,
                    1.2117500360277886,
                    1.1492859656418617,
                    1.1103177943858977,
                    1.0759551479164577,
                    1.0378154955287417,
                    1.0204809008317999,
                    0.9808332191132245
                ],
                "min_energy": [
                    0.8104342725260506,
                    1.9534813639233657,
                    3.2803119330314736,
                    4.74974357820107,
                    6.353320605894968,
                    8.061896552682477,
                    9.8400786438852,
                    11.698311312184163,
                    13.61034246213286,
                    15.594058935401941,
                    17.66966056738387
                ],
                "samples_seen": [
                    [
                        5000.0,
                        10000.0,
                        15000.0,
                        20000.0,
                        25000.0,
                        30000.0,
                        35000.0,
                        40000.0,
                        45000.0,
                        50000.0,
                        55000.0
                    ],
                    [
                        1677.0,
                        2638.0,
                        3380.0,
                        4054.0,
                        4693.0,
                        5323.0,
                        5888.0,
                        6449.0,
                        6992.0,
                        7488.0,
                        8013.0
                    ]
                ]
            }
        },
        {
            "comment": "",
            "name": "time taken",
            "network_parameters": {
                "activation_function": "relu",
                "bias": true,
                "layers": [
                    784,
                    300,
                    10
                ],
                "learning_rate": [
                    0.001,
                    0.001
                ],
                "n_synapses": [
                    235200.0,
                    3000.0
                ],
                "p_connect": [
                    1.0,
                    1.0
                ]
            },
            "results": {
                "accuracy": [
                    80.25999999999999,
                    85.14,
                    87.83999999999999,
                    88.78,
                    88.53999999999999,
                    88.85,
                    89.79,
                    89.18,
                    90.63,
                    90.64999999999999,
                    90.29
                ],
                "energy": [
                    1289.8412346930613,
                    1992.5529364730755,
                    2604.670449146319,
                    3193.473847942305,
                    3784.881200514779,
                    4320.277839791461,
                    4884.034624410837,
                    5396.3278650324455,
                    5919.839702919008,
                    6406.961160425911,
                    6916.071600218479
                ],
                "error": [
                    1.6625711910181122,
                    1.471827524570466,
                    1.3524201208373978,
                    1.2744008831919194,
                    1.2055935453486049,
                    1.1586931097566735,
                    1.108700548538571,
                    1.0738240883858765,
                    1.051905730334475,
                    1.0273697577854546,
                    0.9980425607796778
                ],
                "min_energy": [
                    0.9715692235403797,
                    2.2579307875061096,
                    3.75865195304264,
                    5.4364568934756035,
                    7.254998025719061,
                    9.214173038447193,
                    11.293824535335643,
                    13.437022096886098,
                    15.693876285037074,
                    18.001332441397697,
                    20.358947239747707
                ],
                "samples_seen": [
                    [
                        5000.0,
                        10000.0,
                        15000.0,
                        20000.0,
                        25000.0,
                        30000.0,
                        35000.0,
                        40000.0,
                        45000.0,
                        50000.0,
                        55000.0
                    ],
                    [
                        1730.0,
                        2601.0,
                        3318.0,
                        3979.0,
                        4601.0,
                        5179.0,
                        5761.0,
                        6280.0,
                        6800.0,
                        7287.0,
                        7789.0
                    ]
                ]
            }
        }
    ]
]